Nexagen/.env
Nexagen/__init__.py
Nexagen/cli.py
Nexagen/core.py
Nexagen/prompt.py
Nexagen/utils.py
Nexagen/templates/agent_executor.py.j2
Nexagen/templates/auto_find_mcp_agents.py.j2
Nexagen/templates/bac-orchestrator_agent.py.j2
Nexagen/templates/mcp_client.py.j2
Nexagen/templates/mcp_server.py.j2
Nexagen/templates/orchestrator_agent.py.j2
Nexagen/templates/pipeline.py.j2
Nexagen/templates/pyproject.toml.j2
Nexagen/templates/test_demo.py.j2
nexagen-1.2.3.dist-info/METADATA
nexagen-1.2.3.dist-info/WHEEL
nexagen-1.2.3.dist-info/entry_points.txt
nexagen-1.2.3.dist-info/top_level.txt
nexagen-1.2.3.dist-info/RECORD
