Metadata-Version: 2.4
Name: nexagen
Version: 1.2.3
Summary: Next-Generation Multi-Agent System Builder with MCP Protocol Integration
Home-page: https://github.com/taoxiang-org/nexagen
Author: Chongqing Taoxiang Network Technology Co., Ltd.
Author-email: wei@taoxiang.org
License: MIT
Project-URL: Bug Reports, https://github.com/taoxiang-org/nexagen/issues
Project-URL: Source, https://github.com/taoxiang-org/nexagen
Project-URL: Documentation, https://github.com/taoxiang-org/nexagen#readme
Project-URL: Homepage, https://www.taoxiang.org
Keywords: multi-agent,MCP,automation,AI,orchestration,agent-framework
Classifier: Development Status :: 4 - Beta
Classifier: Intended Audience :: Developers
Classifier: License :: OSI Approved :: MIT License
Classifier: Operating System :: OS Independent
Classifier: Programming Language :: Python :: 3
Classifier: Programming Language :: Python :: 3.8
Classifier: Programming Language :: Python :: 3.9
Classifier: Programming Language :: Python :: 3.10
Classifier: Programming Language :: Python :: 3.11
Classifier: Programming Language :: Python :: 3.12
Classifier: Topic :: Software Development :: Libraries :: Python Modules
Classifier: Topic :: Scientific/Engineering :: Artificial Intelligence
Classifier: Topic :: System :: Distributed Computing
Requires-Python: >=3.8
Requires-Dist: click>=8.0.0
Requires-Dist: jinja2>=3.0.0
Requires-Dist: httpx>=0.24.0
Requires-Dist: requests>=2.28.0
Requires-Dist: python-dotenv>=0.19.0
Requires-Dist: a2a-sdk>=0.1.0
Requires-Dist: mcp>=0.1.0
Requires-Dist: uvicorn>=0.18.0
Dynamic: author
Dynamic: author-email
Dynamic: classifier
Dynamic: description
Dynamic: description-content-type
Dynamic: home-page
Dynamic: keywords
Dynamic: license
Dynamic: project-url
Dynamic: requires-dist
Dynamic: requires-python
Dynamic: summary
